{"_type":"export","__export_format":4,"__export_date":"2021-11-24T14:31:53.339Z","__export_source":"insomnia.desktop.app:v2021.6.0","resources":[{"_id":"req_0bf0842eae3e43ffade006f8cf829549","parentId":"wrk_d4e941c36824449bbf62a5520226ee47","modified":1637764281246,"created":1637764281246,"url":"http://localhost:3001/hello","name":"Hello World","description":"","method":"GET","body":{},"parameters":[],"headers":[],"authentication":{},"metaSortKey":-1637763317130,"isPrivate":false,"settingStoreCookies":true,"settingSendCookies":true,"settingDisableRenderRequestBody":false,"settingEncodeUrl":true,"settingRebuildPath":true,"settingFollowRedirects":"global","_type":"request"},{"_id":"wrk_d4e941c36824449bbf62a5520226ee47","parentId":null,"modified":1637764281230,"created":1637764281230,"name":"TechNine","description":"","scope":"collection","_type":"workspace"},{"_id":"req_7fcdee6ecf474dd1b61ef87c4077f7ed","parentId":"wrk_d4e941c36824449bbf62a5520226ee47","modified":1637764281244,"created":1637764281244,"url":"http://localhost:3001/sortnum","name":"Sort Number","description":"","method":"POST","body":{"mimeType":"application/json","text":"{\n\t\"numArr\":[3,2,534,3242,132123,4,4.1234,41212]\n}"},"parameters":[],"headers":[{"name":"Content-Type","value":"application/json","id":"pair_ca6fd9ac6a8c4b77b76839b6c1d86905"}],"authentication":{},"metaSortKey":-1637763196368,"isPrivate":false,"settingStoreCookies":true,"settingSendCookies":true,"settingDisableRenderRequestBody":false,"settingEncodeUrl":true,"settingRebuildPath":true,"settingFollowRedirects":"global","_type":"request"},{"_id":"env_d898ae52e63b4f2d89df83b652fc6165","parentId":"wrk_d4e941c36824449bbf62a5520226ee47","modified":1637764281234,"created":1637764281234,"name":"Base Environment","data":{},"dataPropertyOrder":null,"color":null,"isPrivate":false,"metaSortKey":1637763182145,"_type":"environment"},{"_id":"jar_ac37e252b8cf486daaf1c11f92b657c2","parentId":"wrk_d4e941c36824449bbf62a5520226ee47","modified":1637764281238,"created":1637764281238,"name":"Default Jar","cookies":[],"_type":"cookie_jar"},{"_id":"spc_afde1ad713f74baa9abb39ce16bfef20","parentId":"wrk_d4e941c36824449bbf62a5520226ee47","modified":1637764281266,"created":1637764281240,"fileName":"TechNine","contents":"","contentType":"yaml","_type":"api_spec"}]}